[
    {
        "recipeName" : "Sausage and Mash", 
        "recipeId" : "917445a8-6508-4152-b016-28affa2030c0",
        "image" : "URL",
        "imageType" : "string",
        "ingredients" : [
            {"itemName" : "sausages", "amount" : 4, "units" : "unit" },
            {"itemName" :"potatos","amount" :  2, "units" : "unit"},
            {"itemName" :"gravy" ,"amount" : 500, "units" : "ml"},
            {"itemName" :"mushrooms","amount" : 300, "units" : "g"},
            {"itemName" :"onions","amount" : 0.5, "units": "unit"}
        ],
        "instructions" : ["Heat Oven", "Cook Sausages", "Mash Potatos", "Add Gravy"]
    },
    {
        "recipeName" : "string", 
        "recipeId" : "3",
        "image" : "URL",
        "imageType" : "string",
        "ingredients" : [
            {"itemName" : "sausages", "amount" : 4, "units" : "unit" },
            {"itemName" :"potatos","amount" :  2, "units" : "unit"},
            {"itemName" :"gravy" ,"amount" : 500, "units" : "ml"},
            {"itemName" :"mushrooms","amount" : 300, "units" : "g"},
            {"itemName" :"onions","amount" : 0.5, "units": "unit"}
        ],
        "instructions" : ["Heat Oven", "Cook Sausages", "Mash Potatos", "Add Gravy"]
    },
    {
        "recipeName" : "string", 
        "recipeId" : "4",
        "image" : "URL",
        "imageType" : "string",
        "ingredients" : [
            {"itemName" : "sausages", "amount" : 4, "units" : "unit" },
            {"itemName" :"potatos","amount" :  2, "units" : "unit"},
            {"itemName" :"gravy" ,"amount" : 500, "units" : "ml"},
            {"itemName" :"mushrooms","amount" : 300, "units" : "g"},
            {"itemName" :"onions","amount" : 0.5, "units": "unit"}
        ],
        "instructions" : ["Heat Oven", "Cook Sausages", "Mash Potatos", "Add Gravy"]
    },
    {
        "recipeName" : "string", 
        "recipeId" : "5",
        "image" : "URL",
        "imageType" : "string",
        "ingredients" : [
            {"itemName" : "sausages", "amount" : 4, "units" : "unit" },
            {"itemName" :"potatos","amount" :  2, "units" : "unit"},
            {"itemName" :"gravy" ,"amount" : 500, "units" : "ml"},
            {"itemName" :"mushrooms","amount" : 300, "units" : "g"},
            {"itemName" :"onions","amount" : 0.5, "units": "unit"}
        ],
        "instructions" : ["Heat Oven", "Cook Sausages", "Mash Potatos", "Add Gravy"]
    },
    {
        "recipeName" : "string", 
        "recipeId" : "6",
        "image" : "URL",
        "imageType" : "string",
        "ingredients" : [
            {"itemName" : "sausages", "amount" : 4, "units" : "unit" },
            {"itemName" :"potatos","amount" :  2, "units" : "unit"},
            {"itemName" :"gravy" ,"amount" : 500, "units" : "ml"},
            {"itemName" :"mushrooms","amount" : 300, "units" : "g"},
            {"itemName" :"onions","amount" : 0.5, "units": "unit"}
        ],
        "instructions" : ["Heat Oven", "Cook Sausages", "Mash Potatos", "Add Gravy"]
    }
]